pugna/__init__.py
pugna/activations.py
pugna/callbacks.py
pugna/data.py
pugna/explorer.py
pugna/layers.py
pugna/learning_rate_schedulers.py
pugna/logger.py
pugna/model_utils.py
pugna/pugna_fit_cli.py
pugna/trainer.py
pugna/training_utils.py
pugna/models/__init__.py
pugna/models/mscalednn.py
pugna-0.2.9.data/scripts/pugna_fit
pugna-0.2.9.data/scripts/pugna_scale_data
pugna-0.2.9.dist-info/LICENSE
pugna-0.2.9.dist-info/METADATA
pugna-0.2.9.dist-info/WHEEL
pugna-0.2.9.dist-info/top_level.txt
pugna-0.2.9.dist-info/RECORD
