Metadata-Version: 2.1
Name: pugna
Version: 0.2.9
Summary: A lightweight package to perform regression with neural nets
Home-page: https://gitlab.com/SpaceTimeKhantinuum/pugna
Author: Sebastian Khan
Author-email: KhanS22@Cardiff.ac.uk
License: UNKNOWN
Platform: UNKNOWN
Classifier: Programming Language :: Python :: 3
Requires-Python: >=3.6
